metar2bufr/__init__.py
metar2bufr/generic_metar_bufr_encoder.py
metar2bufr/metar_bufr_encoder.py
metar2bufr/wigos_metar_bufr_encoder.py
metar2bufr/csv2bufr/setup.py
metar2bufr/csv2bufr/build/lib/csv2bufr/__init__.py
metar2bufr/csv2bufr/build/lib/csv2bufr/cli.py
metar2bufr/csv2bufr/build/lib/csv2bufr/pygeoapi_plugin.py
metar2bufr/csv2bufr/csv2bufr/__init__.py
metar2bufr/csv2bufr/csv2bufr/cli.py
metar2bufr/csv2bufr/csv2bufr/pygeoapi_plugin.py
metar2bufr/csv2bufr/docs/source/conf.py
metar2bufr/csv2bufr/tests/test_csv2bufr.py
metar2bufr/metarDecoder/__init__.py
metar2bufr/metarDecoder/metarDecoders.py
metar2bufr/metarDecoder/tpg.py
metar2bufr/metarDecoder/xmlConfig.py
metar2bufr/metarDecoder/xmlUtilities.py
metar2bufr/resources/307051_metar_mapping.json
metar2bufr/resources/__init__.py
metar2bufr/resources/icao-metar-mappings.json
metar2bufr/resources/metar-mappings.json
metar2bufr/resources/metar-mappings2.json
metar2bufr-0.0.2.59.dist-info/LICENSE
metar2bufr-0.0.2.59.dist-info/METADATA
metar2bufr-0.0.2.59.dist-info/WHEEL
metar2bufr-0.0.2.59.dist-info/top_level.txt
metar2bufr-0.0.2.59.dist-info/RECORD
