Metadata-Version: 2.1
Name: metar2bufr
Version: 0.0.2.59
Summary: Package for converting METAR TAC messages or an individual METAR message to BUFR4
Author-email: Alexander Thompson <alexander.thompson@noaa.gov>
Project-URL: Homepage, https://github.com/pypa/sampleproject
Project-URL: Bug Tracker, https://github.com/pypa/sampleproject/issues
Keywords: WMO,METAR,FM-15,BUFR,decoding,weather,observations
Classifier: Development Status :: 1 - Planning
Requires-Python: >=3.7
License-File: LICENSE
